unumcharfield/__init__.py
unumcharfield/forms.py
unumcharfield/models.py
unumcharfield/validators.py
unumcharfield/demo/__init__.py
unumcharfield/demo/admin.py
unumcharfield/demo/apps.py
unumcharfield/demo/forms.py
unumcharfield/demo/models.py
unumcharfield/demo/urls.py
unumcharfield/demo/views.py
unumcharfield/demo/templates/demo/unumcharfieldtest_form.html
unumcharfield/demo/templates/demo/unumcharfieldtest_list.html
unumcharfield/unum/__init__.py
unumcharfield/unum/units/__init__.py
unumcharfield/unum/units/custom/__init__.py
unumcharfield/unum/units/others/__init__.py
unumcharfield/unum/units/si/__init__.py
unumcharfield/unum/units/si/base.py
unumcharfield/unum/units/si/derived.py
django_unumcharfield-0.3.dist-info/LICENSE
django_unumcharfield-0.3.dist-info/METADATA
django_unumcharfield-0.3.dist-info/WHEEL
django_unumcharfield-0.3.dist-info/top_level.txt
django_unumcharfield-0.3.dist-info/RECORD
